<annotation>
	<folder>JPEGImages</folder>
	<filename>0064.jpg</filename>
	<path>D:\0task\00data\JPEGImages\0064.jpg</path>
	<source>
		<database>Unknown</database>
	</source>
	<size>
		<width>720</width>
		<height>1280</height>
		<depth>3</depth>
	</size>
	<segmented>0</segmented>
	<object>
		<name>imgbutton</name>
		<pose>Unspecified</pose>
		<truncated>0</truncated>
		<difficult>0</difficult>
		<bndbox>
			<xmin>313</xmin>
			<ymin>1183</ymin>
			<xmax>408</xmax>
			<ymax>1271</ymax>
		</bndbox>
	</object>
	<object>
		<name>imgbutton</name>
		<pose>Unspecified</pose>
		<truncated>0</truncated>
		<difficult>0</difficult>
		<bndbox>
			<xmin>627</xmin>
			<ymin>60</ymin>
			<xmax>697</xmax>
			<ymax>134</ymax>
		</bndbox>
	</object>
	<object>
		<name>textview</name>
		<pose>Unspecified</pose>
		<truncated>1</truncated>
		<difficult>0</difficult>
		<bndbox>
			<xmin>1</xmin>
			<ymin>926</ymin>
			<xmax>720</xmax>
			<ymax>1172</ymax>
		</bndbox>
	</object>
	<object>
		<name>imgview</name>
		<pose>Unspecified</pose>
		<truncated>0</truncated>
		<difficult>0</difficult>
		<bndbox>
			<xmin>13</xmin>
			<ymin>946</ymin>
			<xmax>118</xmax>
			<ymax>1044</ymax>
		</bndbox>
	</object>
	<object>
		<name>nav</name>
		<pose>Unspecified</pose>
		<truncated>1</truncated>
		<difficult>0</difficult>
		<bndbox>
			<xmin>1</xmin>
			<ymin>1165</ymin>
			<xmax>720</xmax>
			<ymax>1280</ymax>
		</bndbox>
	</object>
</annotation>
